[ { "prover": "why3:Alt-Ergo,2.3.0", "verdict": "timeout", "time": 10. },
  { "prover": "script", "verdict": "valid" },
  { "header": "Range", "tactic": "Wp.range",
    "params": { "inf": 0, "sup": 15 },
    "select": { "select": "inside-goal", "occur": 0,
                "target": "adc_fake_regs_4[id_0][15]",
                "pattern": "[][]15$adc_fake_regs$id" },
    "children": { "Lower 0": [ { "prover": "qed", "verdict": "valid" } ],
                  "Value 0": [ { "prover": "why3:Alt-Ergo,2.3.0",
                                 "verdict": "valid", "time": 0.0366,
                                 "steps": 42 } ],
                  "Value 1": [ { "prover": "why3:Alt-Ergo,2.3.0",
                                 "verdict": "valid", "time": 0.0994,
                                 "steps": 86 } ],
                  "Value 2": [ { "prover": "why3:Alt-Ergo,2.3.0",
                                 "verdict": "valid", "time": 0.1763,
                                 "steps": 229 } ],
                  "Value 3": [ { "prover": "why3:Alt-Ergo,2.3.0",
                                 "verdict": "valid", "time": 0.1182,
                                 "steps": 232 } ],
                  "Value 4": [ { "prover": "why3:Alt-Ergo,2.3.0",
                                 "verdict": "valid", "time": 0.6315,
                                 "steps": 889 } ],
                  "Value 5": [ { "prover": "why3:Alt-Ergo,2.3.0",
                                 "verdict": "valid", "time": 0.2639,
                                 "steps": 320 } ],
                  "Value 6": [ { "prover": "why3:Alt-Ergo,2.3.0",
                                 "verdict": "valid", "time": 0.8383,
                                 "steps": 1543 } ],
                  "Value 7": [ { "prover": "why3:Alt-Ergo,2.3.0",
                                 "verdict": "valid", "time": 0.7042,
                                 "steps": 1171 } ],
                  "Value 8": [ { "prover": "why3:Alt-Ergo,2.3.0",
                                 "verdict": "valid", "time": 1.1705,
                                 "steps": 1197 } ],
                  "Value 9": [ { "prover": "why3:Alt-Ergo,2.3.0",
                                 "verdict": "valid", "time": 1.0881,
                                 "steps": 1374 } ],
                  "Value 10": [ { "prover": "why3:Alt-Ergo,2.3.0",
                                  "verdict": "valid", "time": 1.6158,
                                  "steps": 1930 } ],
                  "Value 11": [ { "prover": "why3:Alt-Ergo,2.3.0",
                                  "verdict": "valid", "time": 1.8201,
                                  "steps": 1941 } ],
                  "Value 12": [ { "prover": "why3:Alt-Ergo,2.3.0",
                                  "verdict": "valid", "time": 4.1842,
                                  "steps": 2436 } ],
                  "Value 13": [ { "prover": "why3:Alt-Ergo,2.3.0",
                                  "verdict": "valid", "time": 3.483,
                                  "steps": 2123 } ],
                  "Value 14": [ { "prover": "why3:Alt-Ergo,2.3.0",
                                  "verdict": "valid", "time": 3.0983,
                                  "steps": 1792 } ],
                  "Value 15": [ { "prover": "why3:Alt-Ergo,2.3.0",
                                  "verdict": "valid", "time": 3.12,
                                  "steps": 1949 } ],
                  "Upper 15": [ { "prover": "qed", "verdict": "valid" } ] } } ]
